hkpkg.py
hkpkg-0.0.2.dist-info/METADATA
hkpkg-0.0.2.dist-info/WHEEL
hkpkg-0.0.2.dist-info/licenses/LICENSE
hkpkg-0.0.2.dist-info/RECORD
