Metadata-Version: 2.1
Name: hkpkg
Version: 0.0.2
Summary: A small example package
Project-URL: Homepage, https://github.com/hridayK/demo_pkg
Project-URL: Bug Tracker, https://github.com/hridayK/demo_pkg/issues
Author-email: Hriday Keswani <hridaykeswnai@gmail.com>
License-File: LICENSE
Classifier: License :: OSI Approved :: MIT License
Classifier: Operating System :: OS Independent
Classifier: Programming Language :: Python :: 3
Requires-Python: >=3.7
